pyspotui/__init__.py
pyspotui/__main__.py
pyspotui/config.py
pyspotui/helpers.py
pyspotui/main.py
pyspotui/spotify_warper.py
pyspotui-1.0.1.dist-info/METADATA
pyspotui-1.0.1.dist-info/WHEEL
pyspotui-1.0.1.dist-info/entry_points.txt
pyspotui-1.0.1.dist-info/top_level.txt
pyspotui-1.0.1.dist-info/RECORD
